spotlight_monitor/__init__.py
spotlight_monitor/client.py
spotlight_monitor/exceptions.py
spotlight_monitor/middleware.py
spotlight_monitor/models.py
spotlight_monitor/validators.py
spotlight_monitor/integrations/__init__.py
spotlight_monitor/integrations/airflow.py
spotlight_monitor/integrations/fastapi.py
spotlight_monitor-0.5.1.dist-info/METADATA
spotlight_monitor-0.5.1.dist-info/WHEEL
spotlight_monitor-0.5.1.dist-info/top_level.txt
spotlight_monitor-0.5.1.dist-info/RECORD
